detettore.py
scripts/__init__.py
scripts/bamstats.py
scripts/combineVCFs.py
scripts/strumenti.py
detettore-2.0.3.dist-info/entry_points.txt
detettore-2.0.3.dist-info/LICENSE.txt
detettore-2.0.3.dist-info/WHEEL
detettore-2.0.3.dist-info/METADATA
detettore-2.0.3.dist-info/RECORD
